{
  "url": "https://www.idealista.com/inmueble/107291343/",
  "locationSlug": "port-d-andratx",
  "typeOfRental": "temporal",
  "title": "Alquiler de piso en Port d'Andratx",
  "description": "Piso a estrenar con piscina comunitaria en Puerto de Andratx. -Disponible para alquiler temporal. Disponible a partir de abril para alquiler temporal. Apartamento completamente remodelado en pequeña comunidad con piscina, ubicación privilegiada y vistas al Puerto de Andratx. Este espectacular apartamento ofrece magníficas vistas y se encuentra a pocos pasos del puerto deportivo de Andratx. Está completamente remodelado con \"todo a estrenar\". Incluye una amplia zona de comedor y salón con cocina integrada y barra americana, grandes ventanales a la terraza orientada al sur, barbacoa, dos dormitorios, dos baños. Aire acondicionado frío/calor, estufa de leña. Vivir en el corazón de Puerto Andratx.",
  "isAttic": false,
  "meters": 105,
  "rooms": 2,
  "price": 2200,
  "monthsDeposit": 2,
  "specifications": [
    "Balcón",
    "Segunda mano/buen estado",
    "Amueblado y cocina equipada",
    "Aire acondicionado",
    "Piscina",
    "Vistas al mar"
  ],
  "bathrooms": 1,
  "parking": true,
  "parkingMonthPrice": 0,
  "floor": 1,
  "hasElevator": false,
  "energyConsumption": "F",
  "energyEmission": "F",
  "exactCoordinates": false,
  "latitude": 39.5514891,
  "longitude": 2.3788571
}